smi_python_runner/__init__.py
smi_python_runner/main.py
smi_python_runner/project.py
smi_python_runner/runner_application.py
smi_python_runner/logging/__init__.py
smi_python_runner/logging/setup.py
smi_python_runner/modules/__init__.py
smi_python_runner/modules/loader.py
smi_python_runner/runners/__init__.py
smi_python_runner/runners/application_base_runner.py
smi_python_runner/services/__init__.py
smi_python_runner/services/arguments_register_service.py
smi_python_runner/services/runner_register_service.py
test/__init__.py
test/it_main.py
test/runner_x.py
smi_python_runner-1.3.0.dist-info/LICENSE
smi_python_runner-1.3.0.dist-info/METADATA
smi_python_runner-1.3.0.dist-info/WHEEL
smi_python_runner-1.3.0.dist-info/top_level.txt
smi_python_runner-1.3.0.dist-info/RECORD
