Metadata-Version: 2.1
Name: smi-python-runner
Version: 1.3.0
Summary: setmy.info Python runner library.
Home-page: https://github.com/setmy-info/python-runner
Author: Imre Tabur
Author-email: info@setmy.info
License: MIT
License-File: LICENSE
Requires-Dist: smi-python-commons ==0.3.3
